autotime/__init__.py
axil_autotime-0.3.dist-info/LICENSE
axil_autotime-0.3.dist-info/METADATA
axil_autotime-0.3.dist-info/WHEEL
axil_autotime-0.3.dist-info/top_level.txt
axil_autotime-0.3.dist-info/RECORD
