Metadata-Version: 2.1
Name: axil-autotime
Version: 0.3
Summary: An improved version of Time everything in IPython by Phillip Cloud
Home-page: https://github.com/cpcloud/ipython-autotime
Author: Lev Maximov
License: Apache
Classifier: Environment :: Console
Classifier: Intended Audience :: Developers
Classifier: Intended Audience :: Science/Research
Classifier: Intended Audience :: Education
Classifier: License :: OSI Approved :: Apache Software License
Classifier: Operating System :: OS Independent
Classifier: Programming Language :: Python
Classifier: Topic :: Scientific/Engineering
Classifier: Topic :: Utilities
License-File: LICENSE
Requires-Dist: ipython
